pdhs/__init__.py
pdhs/base_api.py
pdhs/countries.py
pdhs/datasets.py
pdhs/download.py
pdhs/geometry.py
pdhs/indicators.py
pdhs/info.py
pdhs/publications.py
pdhs/surveys.py
pdhs/tags.py
pdhs/updates.py
pdhs/tests/test_base_api.py
pdhs/tests/test_download.py
pdhs-0.1.6.dist-info/licenses/LICENSE
pdhs-0.1.6.dist-info/licenses/LICENSE.md
pdhs-0.1.6.dist-info/METADATA
pdhs-0.1.6.dist-info/WHEEL
pdhs-0.1.6.dist-info/top_level.txt
pdhs-0.1.6.dist-info/RECORD
