Metadata-Version: 2.4
Name: pdhs
Version: 0.1.6
Summary: A Python package for accessing and analyzing Demographic and Health Survey (DHS) data.
Author-email: Adejumo Ridwan Suleiman <adejumo999@gmail.com>
Maintainer-email: Adejumo Ridwan Suleiman <adejumo999@gmail.com>
License-Expression: MIT
Requires-Python: >=3.9
License-File: LICENSE
License-File: LICENSE.md
Requires-Dist: git-filter-repo>=2.38.0
Requires-Dist: httpx>=0.24.0
Requires-Dist: mkdocs>=1.6.1
Requires-Dist: mkdocs-material>=9.6.16
Requires-Dist: mkdocstrings[python]>=0.30.0
Requires-Dist: pandas>=1.3.0
Requires-Dist: pdoc>=15.0.4
Requires-Dist: playwright>=1.20.0
Requires-Dist: polars>=0.18.0
Requires-Dist: pyarrow>=8.0.0
Requires-Dist: pygments>=2.19.1
Requires-Dist: pyreadstat>=1.1.0
Requires-Dist: pytest>=6.2.0
Requires-Dist: python-dotenv>=0.19.0
Requires-Dist: requests>=2.25.0
Requires-Dist: ruff>=0.0.200
Dynamic: license-file
